__nitter__/__init__.py
__nitter__/nitter.py
__nitter__/nitter_scraper.py
__nitter__/nltk_init.py
__nitter__/sentiment_stuff.py
__nitter__/query/bank_queries.csv
__nitter__/query/space.csv
__nitter__/sentiment_dictionaries/afinn.csv
__nitter__/sentiment_dictionaries/bing.csv
__nitter__/sentiment_dictionaries/nrc.csv
__nitter__/sentiment_dictionaries/nrc2.csv
nitter_miner-0.1.0.dist-info/METADATA
nitter_miner-0.1.0.dist-info/WHEEL
nitter_miner-0.1.0.dist-info/entry_points.txt
nitter_miner-0.1.0.dist-info/top_level.txt
nitter_miner-0.1.0.dist-info/RECORD
