Metadata-Version: 2.1
Name: nitter-miner
Version: 0.1.0
Summary: cli utility for data mining https://nitter.net/serach
Home-page: https://github.com/hashirkz/twitter_scraper
Author: hashirkz
Author-email: hashirxkhan1@gmail.com
Classifier: Programming Language :: Python :: 3
Classifier: Operating System :: POSIX
Requires-Dist: numpy (==1.23.0)
Requires-Dist: pandas (==2.0.2)
Requires-Dist: bs4 (==0.0.1)
Requires-Dist: requests (==2.28.1)
Requires-Dist: tabulate (==0.9.0)
Requires-Dist: langdetect (==1.0.9)
Requires-Dist: emoji (==1.7.0)
Requires-Dist: text2emotion (==0.0.5)
Requires-Dist: nltk (==3.8.1)
Requires-Dist: transformers (==4.30.2)
Requires-Dist: xformers (==0.0.20)
Requires-Dist: torch (==2.0.1)
Requires-Dist: pip-system-certs (==4.0)
